{
    "abstract": null,
    "arxivId": "1601.03411",
    "authors": [
        {
            "authorId": "48047658",
            "name": "A. MacFie",
            "url": "https://www.semanticscholar.org/author/48047658"
        }
    ],
    "citationVelocity": 0,
    "citations": [
        {
            "arxivId": null,
            "authors": [],
            "doi": null,
            "intent": [],
            "isInfluential": false,
            "paperId": "3cb7b4548131399cbecad725020ac94abe21bfbc",
            "title": "Project-team Algo Algorithms Rocquencourt",
            "url": "https://www.semanticscholar.org/paper/3cb7b4548131399cbecad725020ac94abe21bfbc",
            "venue": "",
            "year": null
        }
    ],
    "corpusId": 2760828,
    "doi": "10.1007/978-3-319-41649-6_29",
    "fieldsOfStudy": [
        "Computer Science"
    ],
    "influentialCitationCount": 0,
    "isOpenAccess": false,
    "isPublisherLicensed": true,
    "is_open_access": false,
    "is_publisher_licensed": true,
    "numCitedBy": 1,
    "numCiting": 47,
    "paperId": "dbacf96c610a071a721b5d8fe09a53e38816505f",
    "references": [
        {
            "arxivId": "1510.03370",
            "authors": [
                {
                    "authorId": "1740494",
                    "name": "Scott Garrabrant"
                },
                {
                    "authorId": "1409258422",
                    "name": "Tsvi Benson-Tilsen"
                },
                {
                    "authorId": "48671078",
                    "name": "Siddharth Bhaskar"
                },
                {
                    "authorId": "2756886",
                    "name": "A. Demski"
                },
                {
                    "authorId": "1409258438",
                    "name": "Joanna Garrabrant"
                },
                {
                    "authorId": "1409258442",
                    "name": "George Koleszarik"
                },
                {
                    "authorId": "2068801685",
                    "name": "Evan Lloyd"
                }
            ],
            "doi": "10.1007/978-3-319-41649-6_20",
            "intent": [],
            "isInfluential": false,
            "paperId": "7bca1c33a7cdbd168913cbdef454470ffc8bc8ad",
            "title": "Asymptotic Logical Uncertainty and the Benford Test",
            "url": "https://www.semanticscholar.org/paper/7bca1c33a7cdbd168913cbdef454470ffc8bc8ad",
            "venue": "AGI",
            "year": 2015
        },
        {
            "arxivId": null,
            "authors": [
                {
                    "authorId": "2285289430",
                    "name": "Frank Vega"
                }
            ],
            "doi": null,
            "intent": [],
            "isInfluential": false,
            "paperId": "7acb41e392e98c0cad048bd04074a9a256e597f6",
            "title": "The P versus NP Problem",
            "url": "https://www.semanticscholar.org/paper/7acb41e392e98c0cad048bd04074a9a256e597f6",
            "venue": "ArXiv",
            "year": 2015
        },
        {
            "arxivId": null,
            "authors": [
                {
                    "authorId": "2756886",
                    "name": "A. Demski"
                }
            ],
            "doi": "10.1007/978-3-642-35506-6_6",
            "intent": [],
            "isInfluential": false,
            "paperId": "a8cd9738c344730d76f4f55a037c399aa7280bd1",
            "title": "Logical Prior Probability",
            "url": "https://www.semanticscholar.org/paper/a8cd9738c344730d76f4f55a037c399aa7280bd1",
            "venue": "AGI",
            "year": 2012
        },
        {
            "arxivId": "1209.2620",
            "authors": [
                {
                    "authorId": "144154444",
                    "name": "Marcus Hutter"
                },
                {
                    "authorId": "34654269",
                    "name": "J. Lloyd"
                },
                {
                    "authorId": "34746380",
                    "name": "K. S. Ng"
                },
                {
                    "authorId": "1742809",
                    "name": "William T. B. Uther"
                }
            ],
            "doi": "10.1016/J.JAL.2013.03.003",
            "intent": [],
            "isInfluential": false,
            "paperId": "b06dc2c36e021e0460e4481c1a66983311ae9590",
            "title": "Probabilities on Sentences in an Expressive Logic",
            "url": "https://www.semanticscholar.org/paper/b06dc2c36e021e0460e4481c1a66983311ae9590",
            "venue": "J. Appl. Log.",
            "year": 2012
        },
        {
            "arxivId": "1108.1791",
            "authors": [
                {
                    "authorId": "20996436",
                    "name": "S. Aaronson"
                }
            ],
            "doi": null,
            "intent": [],
            "isInfluential": false,
            "paperId": "5a4b99fe9a9c8614616141b19d85827eda06bf50",
            "title": "Why Philosophers Should Care About Computational Complexity",
            "url": "https://www.semanticscholar.org/paper/5a4b99fe9a9c8614616141b19d85827eda06bf50",
            "venue": "Electron. Colloquium Comput. Complex.",
            "year": 2011
        },
        {
            "arxivId": null,
            "authors": [
                {
                    "authorId": "1728571",
                    "name": "R. Lipton"
                }
            ],
            "doi": "10.5860/choice.48-5137",
            "intent": [],
            "isInfluential": false,
            "paperId": "3c01ca6d1ebf5efe7463b027d26b9ab3d4b21f4a",
            "title": "The P=NP Question and G\u00f6del\u2019s Lost Letter",
            "url": "https://www.semanticscholar.org/paper/3c01ca6d1ebf5efe7463b027d26b9ab3d4b21f4a",
            "venue": "",
            "year": 2010
        },
        {
            "arxivId": null,
            "authors": [
                {
                    "authorId": "2992198",
                    "name": "D. Fallis"
                }
            ],
            "doi": "10.1515/9783110322583.157",
            "intent": [],
            "isInfluential": false,
            "paperId": "0c5452dcf97d24aedf637189a6eeb7c74ea1c746",
            "title": "Probabilistic Proofs and the Collective Epistemic Goals of Mathematicians",
            "url": "https://www.semanticscholar.org/paper/0c5452dcf97d24aedf637189a6eeb7c74ea1c746",
            "venue": "",
            "year": 2010
        },
        {
            "arxivId": null,
            "authors": [
                {
                    "authorId": "1738080",
                    "name": "B. Goertzel"
                }
            ],
            "doi": "10.2991/AGI.2010.17",
            "intent": [],
            "isInfluential": false,
            "paperId": "b19ec6b651ec820b0f18f29fed8a0173ac5ec29d",
            "title": "Toward a Formal Characterization of Real-World General Intelligence",
            "url": "https://www.semanticscholar.org/paper/b19ec6b651ec820b0f18f29fed8a0173ac5ec29d",
            "venue": "AGI 2010",
            "year": 2010
        },
        {
            "arxivId": null,
            "authors": [
                {
                    "authorId": "2037704",
                    "name": "Jacob Burnim"
                },
                {
                    "authorId": "1953263",
                    "name": "Nicholas Jalbert"
                },
                {
                    "authorId": "2844231",
                    "name": "C. Stergiou"
                },
                {
                    "authorId": "145741786",
                    "name": "Koushik Sen"
                }
            ],
            "doi": "10.1109/ASE.2009.87",
            "intent": [],
            "isInfluential": false,
            "paperId": "448655935730eb854bddd9ee263c9aef39e2db2e",
            "title": "Looper: Lightweight Detection of Infinite Loops at Runtime",
            "url": "https://www.semanticscholar.org/paper/448655935730eb854bddd9ee263c9aef39e2db2e",
            "venue": "2009 IEEE/ACM International Conference on Automated Software Engineering",
            "year": 2009
        },
        {
            "arxivId": null,
            "authors": [
                {
                    "authorId": "2417095",
                    "name": "D. Spielman"
                },
                {
                    "authorId": "144461956",
                    "name": "S. Teng"
                }
            ],
            "doi": "10.1145/1562764.1562785",
            "intent": [
                "methodology"
            ],
            "isInfluential": false,
            "paperId": "79ad6c34e2c7287b7673644f8664ba0d0adaf59e",
            "title": "Smoothed analysis: an attempt to explain the behavior of algorithms in practice",
            "url": "https://www.semanticscholar.org/paper/79ad6c34e2c7287b7673644f8664ba0d0adaf59e",
            "venue": "CACM",
            "year": 2009
        },
        {
            "arxivId": null,
            "authors": [
                {
                    "authorId": "2742533",
                    "name": "Sergei N. Art\u00ebmov"
                },
                {
                    "authorId": "2623404",
                    "name": "Roman Kuznets"
                }
            ],
            "doi": "10.1145/1562814.1562821",
            "intent": [],
            "isInfluential": false,
            "paperId": "0925cd4e323b5c09300af22e68a32246ca99781b",
            "title": "Logical omniscience as a computational complexity problem",
            "url": "https://www.semanticscholar.org/paper/0925cd4e323b5c09300af22e68a32246ca99781b",
            "venue": "TARK '09",
            "year": 2009
        },
        {
            "arxivId": null,
            "authors": [
                {
                    "authorId": "1791816",
                    "name": "P. Flajolet"
                },
                {
                    "authorId": "1745921",
                    "name": "R. Sedgewick"
                }
            ],
            "doi": "10.1017/CBO9780511801655",
            "intent": [],
            "isInfluential": false,
            "paperId": "d347dbb4b2eea7fca0183b55112b9cc07faa51ff",
            "title": "Analytic Combinatorics",
            "url": "https://www.semanticscholar.org/paper/d347dbb4b2eea7fca0183b55112b9cc07faa51ff",
            "venue": "",
            "year": 2009
        },
        {
            "arxivId": null,
            "authors": [
                {
                    "authorId": "2740556",
                    "name": "H. Gaifman"
                }
            ],
            "doi": "10.1023/B:SYNT.0000029944.99888.a7",
            "intent": [],
            "isInfluential": false,
            "paperId": "cdc782c073de2bd35a5a5be575db4c59a88b358d",
            "title": "Reasoning with Limited Resources and Assigning Probabilities to Arithmetical Statements",
            "url": "https://www.semanticscholar.org/paper/cdc782c073de2bd35a5a5be575db4c59a88b358d",
            "venue": "Synthese",
            "year": 2004
        },
        {
            "arxivId": null,
            "authors": [
                {
                    "authorId": "2992198",
                    "name": "D. Fallis"
                }
            ],
            "doi": null,
            "intent": [],
            "isInfluential": false,
            "paperId": "bc2188035dcee177549b5766e37d197f59e9c90a",
            "title": "What Do Mathematicians Want? Probabilistic Proofs and the Epistemic Goals of Mathematicians",
            "url": "https://www.semanticscholar.org/paper/bc2188035dcee177549b5766e37d197f59e9c90a",
            "venue": "",
            "year": 2003
        },
        {
            "arxivId": "math/0302333",
            "authors": [
                {
                    "authorId": "1756533",
                    "name": "G. Chaitin"
                }
            ],
            "doi": "10.1007/3-540-45066-1_1",
            "intent": [],
            "isInfluential": false,
            "paperId": "721ea04bd123c8fb9820fd486248ca019617b168",
            "title": "Two Philosophical Applications of Algorithmic Information Theory",
            "url": "https://www.semanticscholar.org/paper/721ea04bd123c8fb9820fd486248ca019617b168",
            "venue": "DMTCS",
            "year": 2003
        },
        {
            "arxivId": null,
            "authors": [
                {
                    "authorId": "1704511",
                    "name": "Lane A. Hemaspaandra"
                }
            ],
            "doi": "10.1145/564585.564599",
            "intent": [],
            "isInfluential": false,
            "paperId": "19693ba54ec87d15fa608caf784cfe097b7474c8",
            "title": "SIGACT news complexity theory column 36",
            "url": "https://www.semanticscholar.org/paper/19693ba54ec87d15fa608caf784cfe097b7474c8",
            "venue": "SIGA",
            "year": 2002
        },
        {
            "arxivId": null,
            "authors": [
                {
                    "authorId": "145808041",
                    "name": "S. Frederick"
                },
                {
                    "authorId": "3070352",
                    "name": "G. Loewenstein"
                },
                {
                    "authorId": "1403607956",
                    "name": "Ted O\u2019Donoghue"
                }
            ],
            "doi": "10.1257/002205102320161311",
            "intent": [],
            "isInfluential": false,
            "paperId": "b2369c0575d060872a7b980315f38103bbaaae1c",
            "title": "Time Discounting and Time Preference: A Critical Review",
            "url": "https://www.semanticscholar.org/paper/b2369c0575d060872a7b980315f38103bbaaae1c",
            "venue": "",
            "year": 2002
        },
        {
            "arxivId": null,
            "authors": [
                {
                    "authorId": "2992198",
                    "name": "D. Fallis"
                }
            ],
            "doi": "10.2307/2940964",
            "intent": [],
            "isInfluential": false,
            "paperId": "c1160ea7edbf5387b45d4c02d9d128458c1f8905",
            "title": "The Epistemic Status of Probabilistic Proof",
            "url": "https://www.semanticscholar.org/paper/c1160ea7edbf5387b45d4c02d9d128458c1f8905",
            "venue": "",
            "year": 1997
        },
        {
            "arxivId": null,
            "authors": [
                {
                    "authorId": "2111973920",
                    "name": "R. Shyamasundar"
                }
            ],
            "doi": "10.1007/BF02837777",
            "intent": [
                "methodology"
            ],
            "isInfluential": false,
            "paperId": "f2c1830eedc095b92a78dc3afa39a36343ed81ad",
            "title": "Introduction to algorithms",
            "url": "https://www.semanticscholar.org/paper/f2c1830eedc095b92a78dc3afa39a36343ed81ad",
            "venue": "",
            "year": 1996
        },
        {
            "arxivId": null,
            "authors": [
                {
                    "authorId": "16802960",
                    "name": "Ho Ngoc Duc"
                }
            ],
            "doi": "10.1007/3-540-61313-7_66",
            "intent": [],
            "isInfluential": false,
            "paperId": "27a6ed7d4da83be51d04dbc6c63ad86cce67397f",
            "title": "Reasoning about Rational, but not Logically Omniscient Agents (Extended Abstract)",
            "url": "https://www.semanticscholar.org/paper/27a6ed7d4da83be51d04dbc6c63ad86cce67397f",
            "venue": "FAPR",
            "year": 1996
        },
        {
            "arxivId": null,
            "authors": [
                {
                    "authorId": "27320299",
                    "name": "R. Pinch"
                }
            ],
            "doi": "10.1090/S0025-5718-1993-1202611-7",
            "intent": [
                "methodology"
            ],
            "isInfluential": false,
            "paperId": "8011b2a77eecd7d800bd14a33ed57a02e5dc5367",
            "title": "The Carmichael Numbers up to 10 15",
            "url": "https://www.semanticscholar.org/paper/8011b2a77eecd7d800bd14a33ed57a02e5dc5367",
            "venue": "",
            "year": 1993
        },
        {
            "arxivId": null,
            "authors": [
                {
                    "authorId": "2367457",
                    "name": "M. Sipser"
                }
            ],
            "doi": "10.1145/129712.129771",
            "intent": [],
            "isInfluential": false,
            "paperId": "ed5299ffbaa9978921b414280457c7a8e8ab226f",
            "title": "The history and status of the P versus NP question",
            "url": "https://www.semanticscholar.org/paper/ed5299ffbaa9978921b414280457c7a8e8ab226f",
            "venue": "STOC '92",
            "year": 1992
        },
        {
            "arxivId": null,
            "authors": [
                {
                    "authorId": "1727290",
                    "name": "P. Boas"
                }
            ],
            "doi": "10.1016/B978-0-444-88071-0.50006-0",
            "intent": [],
            "isInfluential": false,
            "paperId": "0281dcf53024a4064be2d976885c33f741032ca4",
            "title": "Machine models and simulations",
            "url": "https://www.semanticscholar.org/paper/0281dcf53024a4064be2d976885c33f741032ca4",
            "venue": "",
            "year": 1991
        },
        {
            "arxivId": null,
            "authors": [
                {
                    "authorId": "143817739",
                    "name": "J. Leeuwen"
                }
            ],
            "doi": null,
            "intent": [],
            "isInfluential": false,
            "paperId": "b55fda1f58af7fd9ecde8f1dc193ddd6ab6e9d26",
            "title": "Handbook of theoretical computer science - Part A: Algorithms and complexity; Part B: Formal models and semantics",
            "url": "https://www.semanticscholar.org/paper/b55fda1f58af7fd9ecde8f1dc193ddd6ab6e9d26",
            "venue": "",
            "year": 1990
        },
        {
            "arxivId": null,
            "authors": [
                {
                    "authorId": "2352366",
                    "name": "S. Ross"
                }
            ],
            "doi": "10.1080/00401706.1998.10485493",
            "intent": [
                "methodology"
            ],
            "isInfluential": false,
            "paperId": "3d3c82d8989b0053da3fc7b0598cb72457442fd1",
            "title": "Introduction to probability models",
            "url": "https://www.semanticscholar.org/paper/3d3c82d8989b0053da3fc7b0598cb72457442fd1",
            "venue": "",
            "year": 1975
        },
        {
            "arxivId": null,
            "authors": [
                {
                    "authorId": "7326926",
                    "name": "W. Worlton"
                }
            ],
            "doi": "10.13182/NSE70-A19705",
            "intent": [],
            "isInfluential": false,
            "paperId": "7457476bd4719212ab257ad96483a642a35d61bd",
            "title": "The Art of Computer Programming",
            "url": "https://www.semanticscholar.org/paper/7457476bd4719212ab257ad96483a642a35d61bd",
            "venue": "",
            "year": 1968
        },
        {
            "arxivId": null,
            "authors": [
                {
                    "authorId": "29938927",
                    "name": "Hofreiter"
                }
            ],
            "doi": "10.1007/BF01695528",
            "intent": [],
            "isInfluential": false,
            "paperId": "df6a689b4089992e4458aadbf2bd3a3bcf57b1e2",
            "title": "The collected works",
            "url": "https://www.semanticscholar.org/paper/df6a689b4089992e4458aadbf2bd3a3bcf57b1e2",
            "venue": "",
            "year": 1939
        },
        {
            "arxivId": null,
            "authors": [
                {
                    "authorId": "1719968",
                    "name": "N. Soares"
                },
                {
                    "authorId": "1825635",
                    "name": "Benja Fallenstein"
                }
            ],
            "doi": null,
            "intent": [
                "background"
            ],
            "isInfluential": false,
            "paperId": "3ffdc1834c9d210bc328d7414a709aa3b15a8fd0",
            "title": "Questions of Reasoning Under Logical Uncertainty",
            "url": "https://www.semanticscholar.org/paper/3ffdc1834c9d210bc328d7414a709aa3b15a8fd0",
            "venue": "",
            "year": 2015
        },
        {
            "arxivId": null,
            "authors": [
                {
                    "authorId": "145370786",
                    "name": "Paul Christiano"
                }
            ],
            "doi": null,
            "intent": [],
            "isInfluential": false,
            "paperId": "8242530119462a9a8f8601f97a9d889cc60316c7",
            "title": "Non-Omniscience, Probabilistic Inference, and Metamathematics",
            "url": "https://www.semanticscholar.org/paper/8242530119462a9a8f8601f97a9d889cc60316c7",
            "venue": "",
            "year": 2014
        },
        {
            "arxivId": null,
            "authors": [
                {
                    "authorId": "145370786",
                    "name": "Paul Christiano"
                },
                {
                    "authorId": "2542795",
                    "name": "Eliezer Yudkowsky"
                },
                {
                    "authorId": "1881346",
                    "name": "Marcello Herreshoff"
                },
                {
                    "authorId": "2034274",
                    "name": "M. B\u00e1r\u00e1sz"
                }
            ],
            "doi": null,
            "intent": [],
            "isInfluential": false,
            "paperId": "6e6f24ea848f11f308f05385bb1f5a436d7fcbd3",
            "title": "Definability of Truth in Probabilistic Logic ( Early draft )",
            "url": "https://www.semanticscholar.org/paper/6e6f24ea848f11f308f05385bb1f5a436d7fcbd3",
            "venue": "",
            "year": 2013
        },
        {
            "arxivId": null,
            "authors": [
                {
                    "authorId": "1731638",
                    "name": "C. Aykanat"
                },
                {
                    "authorId": "2265542512",
                    "name": "Mustafa Ozdal"
                },
                {
                    "authorId": "1725180",
                    "name": "T. Cormen"
                },
                {
                    "authorId": "2064303000",
                    "name": "C. E. Leiserson"
                },
                {
                    "authorId": "2270842708",
                    "name": "R. L. Rivest"
                },
                {
                    "authorId": "2285789697",
                    "name": "Clifford Stein"
                }
            ],
            "doi": null,
            "intent": [
                "background"
            ],
            "isInfluential": false,
            "paperId": "0fb56551218395cd31d9acec6c9426401a9af96a",
            "title": "Introduction to Analysis of Algorithms",
            "url": "https://www.semanticscholar.org/paper/0fb56551218395cd31d9acec6c9426401a9af96a",
            "venue": "",
            "year": 2008
        },
        {
            "arxivId": null,
            "authors": [
                {
                    "authorId": "2510584",
                    "name": "T. Gowers"
                }
            ],
            "doi": "10.5860/choice.46-3606",
            "intent": [],
            "isInfluential": false,
            "paperId": "a7bae89963046e83ddbcf8be38afee10135e1187",
            "title": "Princeton companion to mathematics",
            "url": "https://www.semanticscholar.org/paper/a7bae89963046e83ddbcf8be38afee10135e1187",
            "venue": "",
            "year": 2008
        },
        {
            "arxivId": null,
            "authors": [
                {
                    "authorId": "144154444",
                    "name": "Marcus Hutter"
                }
            ],
            "doi": null,
            "intent": [
                "methodology"
            ],
            "isInfluential": false,
            "paperId": "4b3439884c4dbac5fc5530ab5afeaf3669e85462",
            "title": "Sequential Decisions based on Algorithmic Probability",
            "url": "https://www.semanticscholar.org/paper/4b3439884c4dbac5fc5530ab5afeaf3669e85462",
            "venue": "",
            "year": 2008
        },
        {
            "arxivId": null,
            "authors": [
                {
                    "authorId": "145341374",
                    "name": "J. Schmidhuber"
                }
            ],
            "doi": "10.1007/978-3-540-68677-4_7",
            "intent": [
                "background"
            ],
            "isInfluential": false,
            "paperId": "402a5f749c99c75c98a626539553c2e4b5939c29",
            "title": "G\u00f6del Machines: Fully Self-referential Optimal Universal Self-improvers",
            "url": "https://www.semanticscholar.org/paper/402a5f749c99c75c98a626539553c2e4b5939c29",
            "venue": "Artificial General Intelligence",
            "year": 2007
        },
        {
            "arxivId": null,
            "authors": [
                {
                    "authorId": "49607811",
                    "name": "M. Trott"
                }
            ],
            "doi": "10.1007/0-387-28815-5",
            "intent": [
                "methodology"
            ],
            "isInfluential": false,
            "paperId": "e37b226e4d51dd3c591a75c1cec7094ea5174049",
            "title": "The Mathematica GuideBook for Symbolics",
            "url": "https://www.semanticscholar.org/paper/e37b226e4d51dd3c591a75c1cec7094ea5174049",
            "venue": "The Mathematica Guidebook",
            "year": 2006
        },
        {
            "arxivId": null,
            "authors": [
                {
                    "authorId": "2242959270",
                    "name": "J. M. Borwein"
                }
            ],
            "doi": null,
            "intent": [],
            "isInfluential": false,
            "paperId": "bb9000a447b6c88cd62a6ac44d7d6b4734d2f022",
            "title": "Mathematics by experiment : plausible reasoning in the 21st century",
            "url": "https://www.semanticscholar.org/paper/bb9000a447b6c88cd62a6ac44d7d6b4734d2f022",
            "venue": "",
            "year": 2004
        },
        {
            "arxivId": null,
            "authors": [
                {
                    "authorId": "73382862",
                    "name": "Julian Havil"
                }
            ],
            "doi": "10.5860/choice.41-0979",
            "intent": [
                "background"
            ],
            "isInfluential": false,
            "paperId": "18cf60a097048bc94445fbd3880509aee9de1840",
            "title": "Gamma: Exploring Euler's Constant",
            "url": "https://www.semanticscholar.org/paper/18cf60a097048bc94445fbd3880509aee9de1840",
            "venue": "",
            "year": 2003
        },
        {
            "arxivId": null,
            "authors": [
                {
                    "authorId": "144156057",
                    "name": "Jon Williamson"
                }
            ],
            "doi": null,
            "intent": [],
            "isInfluential": false,
            "paperId": "3e71b8cfe5bc0e2e61e8319d45a486c54ecd3e2f",
            "title": "Bayesian Networks for Logical Reasoning",
            "url": "https://www.semanticscholar.org/paper/3e71b8cfe5bc0e2e61e8319d45a486c54ecd3e2f",
            "venue": "",
            "year": 2001
        },
        {
            "arxivId": null,
            "authors": [
                {
                    "authorId": "1717349",
                    "name": "D. Knuth"
                }
            ],
            "doi": null,
            "intent": [],
            "isInfluential": false,
            "paperId": "f01fb3a0ea5ebf95f53692e22914c26d4dd6e946",
            "title": "The art of computer programming, volume 3: (2nd ed.) sorting and searching",
            "url": "https://www.semanticscholar.org/paper/f01fb3a0ea5ebf95f53692e22914c26d4dd6e946",
            "venue": "",
            "year": 1998
        },
        {
            "arxivId": null,
            "authors": [
                {
                    "authorId": "2103025253",
                    "name": "Yuri GurevichElectrical"
                }
            ],
            "doi": null,
            "intent": [],
            "isInfluential": false,
            "paperId": "b2377b8d997d0d39116513629699002d49eb5ed8",
            "title": "Feasible Functions",
            "url": "https://www.semanticscholar.org/paper/b2377b8d997d0d39116513629699002d49eb5ed8",
            "venue": "",
            "year": 1993
        },
        {
            "arxivId": null,
            "authors": [
                {
                    "authorId": "1785347",
                    "name": "Carl A. Gunter"
                },
                {
                    "authorId": "145817111",
                    "name": "D. Scott"
                }
            ],
            "doi": null,
            "intent": [],
            "isInfluential": false,
            "paperId": "c21f4046ef7a5cbd540aa8691c8656fd475b03ec",
            "title": "In handbook of theoretical computer science",
            "url": "https://www.semanticscholar.org/paper/c21f4046ef7a5cbd540aa8691c8656fd475b03ec",
            "venue": "",
            "year": 1990
        },
        {
            "arxivId": null,
            "authors": [
                {
                    "authorId": "2246324900",
                    "name": "Jan van Leeuwen"
                }
            ],
            "doi": null,
            "intent": [
                "background"
            ],
            "isInfluential": false,
            "paperId": "47eb977eb17e5f1c405667ee10adcdc250140a1b",
            "title": "Handbook of Theoretical Computer Science, Volume B: Formal Models and Semantics",
            "url": "https://www.semanticscholar.org/paper/47eb977eb17e5f1c405667ee10adcdc250140a1b",
            "venue": "",
            "year": 1990
        },
        {
            "arxivId": null,
            "authors": [
                {
                    "authorId": "52292717",
                    "name": "D. Garber"
                }
            ],
            "doi": "10.5749/j.cttts94f.8",
            "intent": [],
            "isInfluential": false,
            "paperId": "eefa0ccb53adeb9271641de09f669ec0132238b2",
            "title": "Old Evidence and Logical Omniscience in Bayesian Confirmation Theory",
            "url": "https://www.semanticscholar.org/paper/eefa0ccb53adeb9271641de09f669ec0132238b2",
            "venue": "",
            "year": 1983
        },
        {
            "arxivId": null,
            "authors": [
                {
                    "authorId": "2285442215",
                    "name": "Donald William Drury"
                }
            ],
            "doi": null,
            "intent": [
                "methodology"
            ],
            "isInfluential": false,
            "paperId": "5ace35c4419fe3b903a4a216dddccaf94dbb0d4a",
            "title": "The art of computer programming",
            "url": "https://www.semanticscholar.org/paper/5ace35c4419fe3b903a4a216dddccaf94dbb0d4a",
            "venue": "",
            "year": 1983
        },
        {
            "arxivId": null,
            "authors": [
                {
                    "authorId": "1717349",
                    "name": "D. Knuth"
                }
            ],
            "doi": null,
            "intent": [
                "methodology"
            ],
            "isInfluential": false,
            "paperId": "7acf06e8131c4c6f337b7640cad3c6ebc2bf6f1d",
            "title": "The Art of Computer Programming, Vol. 2",
            "url": "https://www.semanticscholar.org/paper/7acf06e8131c4c6f337b7640cad3c6ebc2bf6f1d",
            "venue": "",
            "year": 1981
        }
    ],
    "s2FieldsOfStudy": [
        {
            "category": "Computer Science",
            "source": "external"
        },
        {
            "category": "Computer Science",
            "source": "s2-fos-model"
        },
        {
            "category": "Mathematics",
            "source": "s2-fos-model"
        }
    ],
    "title": "Analysis of Algorithms and Partial Algorithms",
    "topics": [],
    "url": "https://www.semanticscholar.org/paper/dbacf96c610a071a721b5d8fe09a53e38816505f",
    "venue": "Artificial General Intelligence",
    "year": 2016
}