{
    "abstract": "Book sales in Spain have fallen progressively, which requires urgent changes to optimize the sales process as much as possible. This research proposes a new system, called Base of Reasoning in Artificial Intelligence with Natural Language (BRAIN L) focused exclusively on the publishing industry. The new field of knowledge of Artificial Intelligence (AI), Natural Language Processing (NLP), tecnolog\\'ia del Machine Learning is combined with Case-Based Reasoning (CBR) techniques for book recommendations. A model is developed to retrieve similar cases/books supported by NLP techniques for decision making. In addition, policies are implemented to keep the model evaluated by expert reviews, where the system not only learns with new cases, but these cases are real.",
    "arxivId": "2302.00653",
    "authors": [
        {
            "authorId": "2203940895",
            "name": "J. C. M. Sujo",
            "url": "https://www.semanticscholar.org/author/2203940895"
        },
        {
            "authorId": "2263711",
            "name": "E. Golobardes",
            "url": "https://www.semanticscholar.org/author/2263711"
        }
    ],
    "citationVelocity": 0,
    "citations": [
        {
            "arxivId": null,
            "authors": [
                {
                    "authorId": "2188933947",
                    "name": "Elena-Ruxandra Lu\u0163an"
                },
                {
                    "authorId": "1740341",
                    "name": "C. B\u01cedic\u01ce"
                }
            ],
            "doi": "10.15439/2023F8647",
            "intent": [
                "background"
            ],
            "isInfluential": false,
            "paperId": "10d3c9df139772970e9a25367519adc6e1d15f2a",
            "title": "Emotion-Based Literature Books Recommender Systems",
            "url": "https://www.semanticscholar.org/paper/10d3c9df139772970e9a25367519adc6e1d15f2a",
            "venue": "2023 18th Conference on Computer Science and Intelligence Systems (FedCSIS)",
            "year": 2023
        }
    ],
    "corpusId": 256459493,
    "doi": "10.48550/arXiv.2302.00653",
    "fieldsOfStudy": [
        "Computer Science"
    ],
    "influentialCitationCount": 0,
    "isOpenAccess": true,
    "isPublisherLicensed": true,
    "is_open_access": true,
    "is_publisher_licensed": true,
    "numCitedBy": 1,
    "numCiting": 25,
    "paperId": "e5fd81c21f08690469dc9120bcc1e4c2bf28536f",
    "references": [
        {
            "arxivId": null,
            "authors": [
                {
                    "authorId": "2203940895",
                    "name": "J. C. M. Sujo"
                },
                {
                    "authorId": "2263711",
                    "name": "E. Golobardes"
                },
                {
                    "authorId": "1382790348",
                    "name": "X. Vilas\u00eds-Cardona"
                },
                {
                    "authorId": "1406529548",
                    "name": "Virginia Jim\u00e9nez-Ruano"
                },
                {
                    "authorId": "2148290476",
                    "name": "Javier Villasmil L\u00f3pez"
                }
            ],
            "doi": "10.1007/978-3-030-82196-8_25",
            "intent": [
                "methodology"
            ],
            "isInfluential": true,
            "paperId": "63268dc01f12dee3b10347a6545ba53a094415e6",
            "title": "SmartData: An Intelligent Decision Support System to Predict the Readers Permanence in News",
            "url": "https://www.semanticscholar.org/paper/63268dc01f12dee3b10347a6545ba53a094415e6",
            "venue": "IntelliSys",
            "year": 2021
        },
        {
            "arxivId": "2104.00409",
            "authors": [
                {
                    "authorId": "2206292637",
                    "name": "Parfait Atchade Adelomou"
                },
                {
                    "authorId": "2206311443",
                    "name": "Daniel Casado Fauli"
                },
                {
                    "authorId": "2037967783",
                    "name": "Elisabet Golobardes Rib\u00e9"
                },
                {
                    "authorId": "1382790348",
                    "name": "X. Vilas\u00eds-Cardona"
                }
            ],
            "doi": "10.1007/s10462-022-10238-w",
            "intent": [
                "background"
            ],
            "isInfluential": true,
            "paperId": "fbb87549ae55a6b87d15f6b2cd0ad6bc9bfd3223",
            "title": "Quantum case-based reasoning (qCBR)",
            "url": "https://www.semanticscholar.org/paper/fbb87549ae55a6b87d15f6b2cd0ad6bc9bfd3223",
            "venue": "Artificial Intelligence Review",
            "year": 2021
        },
        {
            "arxivId": null,
            "authors": [
                {
                    "authorId": "2119019103",
                    "name": "Haitao Wu"
                },
                {
                    "authorId": "3018038",
                    "name": "B. Zhong"
                },
                {
                    "authorId": "1971663",
                    "name": "B. Medjdoub"
                },
                {
                    "authorId": "98641696",
                    "name": "Xuejiao Xing"
                },
                {
                    "authorId": "2072513979",
                    "name": "Li Jiao"
                }
            ],
            "doi": "10.3390/app10155298",
            "intent": [
                "background",
                "methodology"
            ],
            "isInfluential": true,
            "paperId": "4e223a0864b4f79b21a3b21c2575a589d7c02975",
            "title": "An Ontological Metro Accident Case Retrieval Using CBR and NLP",
            "url": "https://www.semanticscholar.org/paper/4e223a0864b4f79b21a3b21c2575a589d7c02975",
            "venue": "Applied Sciences",
            "year": 2020
        },
        {
            "arxivId": null,
            "authors": [
                {
                    "authorId": "2118961631",
                    "name": "Delu Wang"
                },
                {
                    "authorId": "92773092",
                    "name": "Kaidi Wan"
                },
                {
                    "authorId": "2111665113",
                    "name": "Wenxiao Ma"
                }
            ],
            "doi": "10.1016/j.jenvman.2020.110382",
            "intent": [
                "background"
            ],
            "isInfluential": false,
            "paperId": "747ce3ce3ca8fa94a1f2bfcda5d52695fc532573",
            "title": "Emergency decision-making model of environmental emergencies based on case-based reasoning method.",
            "url": "https://www.semanticscholar.org/paper/747ce3ce3ca8fa94a1f2bfcda5d52695fc532573",
            "venue": "Journal of environmental management",
            "year": 2020
        },
        {
            "arxivId": null,
            "authors": [
                {
                    "authorId": "2094375836",
                    "name": "Tom\u00e1s L\u00f3pez-Solaz"
                },
                {
                    "authorId": "144094175",
                    "name": "J. Jim\u00e9nez"
                },
                {
                    "authorId": "1677738064",
                    "name": "F. Ortega"
                },
                {
                    "authorId": "2056153646",
                    "name": "F. Ros"
                }
            ],
            "doi": null,
            "intent": [
                "methodology"
            ],
            "isInfluential": false,
            "paperId": "62a4c475bb2dcbc2cf8b816cd899c4af0daed605",
            "title": "Una aproximaci\u00f3n al uso de word embeddings en una tarea de similitud de textos en espa\u00f1ol",
            "url": "https://www.semanticscholar.org/paper/62a4c475bb2dcbc2cf8b816cd899c4af0daed605",
            "venue": "Proces. del Leng. Natural",
            "year": 2016
        },
        {
            "arxivId": null,
            "authors": [
                {
                    "authorId": "143845796",
                    "name": "Jeffrey Pennington"
                },
                {
                    "authorId": "2166511",
                    "name": "R. Socher"
                },
                {
                    "authorId": "144783904",
                    "name": "Christopher D. Manning"
                }
            ],
            "doi": "10.3115/v1/D14-1162",
            "intent": [],
            "isInfluential": false,
            "paperId": "f37e1b62a767a307c046404ca96bc140b3e68cb5",
            "title": "GloVe: Global Vectors for Word Representation",
            "url": "https://www.semanticscholar.org/paper/f37e1b62a767a307c046404ca96bc140b3e68cb5",
            "venue": "EMNLP",
            "year": 2014
        },
        {
            "arxivId": null,
            "authors": [
                {
                    "authorId": "144140335",
                    "name": "G. Sidorov"
                },
                {
                    "authorId": "1747784",
                    "name": "Alexander Gelbukh"
                },
                {
                    "authorId": "1403763319",
                    "name": "Helena G\u00f3mez-Adorno"
                },
                {
                    "authorId": "145658132",
                    "name": "David Pinto"
                }
            ],
            "doi": "10.13053/CYS-18-3-2043",
            "intent": [
                "methodology"
            ],
            "isInfluential": false,
            "paperId": "7f74703f583650ec274d25d15e1b51ba084d8661",
            "title": "Soft Similarity and Soft Cosine Measure: Similarity of Features in Vector Space Model",
            "url": "https://www.semanticscholar.org/paper/7f74703f583650ec274d25d15e1b51ba084d8661",
            "venue": "Computaci\u00f3n y Sistemas",
            "year": 2014
        },
        {
            "arxivId": null,
            "authors": [
                {
                    "authorId": "2047446108",
                    "name": "Tomas Mikolov"
                },
                {
                    "authorId": "144105277",
                    "name": "Wen-tau Yih"
                },
                {
                    "authorId": "1681543",
                    "name": "G. Zweig"
                }
            ],
            "doi": null,
            "intent": [
                "background"
            ],
            "isInfluential": false,
            "paperId": "c4fd9c86b2b41df51a6fe212406dda81b1997fd4",
            "title": "Linguistic Regularities in Continuous Space Word Representations",
            "url": "https://www.semanticscholar.org/paper/c4fd9c86b2b41df51a6fe212406dda81b1997fd4",
            "venue": "NAACL",
            "year": 2013
        },
        {
            "arxivId": null,
            "authors": [
                {
                    "authorId": "1986886",
                    "name": "W. H. Gomaa"
                },
                {
                    "authorId": "33838038",
                    "name": "A. Fahmy"
                }
            ],
            "doi": "10.5120/11638-7118",
            "intent": [],
            "isInfluential": false,
            "paperId": "5b5ca878c534aee3882a038ef9e82f46e102131b",
            "title": "A Survey of Text Similarity Approaches",
            "url": "https://www.semanticscholar.org/paper/5b5ca878c534aee3882a038ef9e82f46e102131b",
            "venue": "",
            "year": 2013
        },
        {
            "arxivId": null,
            "authors": [
                {
                    "authorId": "1760816",
                    "name": "Chen-Shu Wang"
                },
                {
                    "authorId": "32065737",
                    "name": "Hengdong Yang"
                }
            ],
            "doi": "10.1016/j.eswa.2011.09.161",
            "intent": [],
            "isInfluential": false,
            "paperId": "b55b0fad9094a95b54c11c47d4aa7a4cbd4174f0",
            "title": "A recommender mechanism based on case-based reasoning",
            "url": "https://www.semanticscholar.org/paper/b55b0fad9094a95b54c11c47d4aa7a4cbd4174f0",
            "venue": "Expert Syst. Appl.",
            "year": 2012
        },
        {
            "arxivId": null,
            "authors": [
                {
                    "authorId": "2109141822",
                    "name": "Yi-Fen Chen"
                }
            ],
            "doi": "10.1016/j.chb.2007.08.004",
            "intent": [
                "background"
            ],
            "isInfluential": false,
            "paperId": "c32e195b8633737953fe0a8e017ad5b789cc5b16",
            "title": "Herd behavior in purchasing books online",
            "url": "https://www.semanticscholar.org/paper/c32e195b8633737953fe0a8e017ad5b789cc5b16",
            "venue": "Comput. Hum. Behav.",
            "year": 2008
        },
        {
            "arxivId": null,
            "authors": [
                {
                    "authorId": "1717197",
                    "name": "P. Chang"
                },
                {
                    "authorId": "2115738245",
                    "name": "Yen-Wen Wang"
                },
                {
                    "authorId": "3349415",
                    "name": "C. Ting"
                },
                {
                    "authorId": "2178142",
                    "name": "Chien-Yuan Lai"
                },
                {
                    "authorId": "2336504",
                    "name": "Chen-Hao Liu"
                }
            ],
            "doi": "10.1016/j.dss.2006.02.014",
            "intent": [
                "background"
            ],
            "isInfluential": false,
            "paperId": "1fd56034671f17981c26e13ba1a48a0dbc695b9a",
            "title": "A hybrid system by evolving case-based reasoning with genetic algorithm in wholesaler's returning book forecasting",
            "url": "https://www.semanticscholar.org/paper/1fd56034671f17981c26e13ba1a48a0dbc695b9a",
            "venue": "Decis. Support Syst.",
            "year": 2006
        },
        {
            "arxivId": null,
            "authors": [
                {
                    "authorId": "1717197",
                    "name": "P. Chang"
                },
                {
                    "authorId": "2178142",
                    "name": "Chien-Yuan Lai"
                }
            ],
            "doi": "10.1016/j.eswa.2005.01.018",
            "intent": [
                "methodology"
            ],
            "isInfluential": false,
            "paperId": "cd8de7c0e6366653b6d7ab6c09279a54331b0038",
            "title": "A hybrid system combining self-organizing maps with case-based reasoning in wholesaler's new-release book forecasting",
            "url": "https://www.semanticscholar.org/paper/cd8de7c0e6366653b6d7ab6c09279a54331b0038",
            "venue": "Expert Syst. Appl.",
            "year": 2005
        },
        {
            "arxivId": null,
            "authors": [
                {
                    "authorId": "98631536",
                    "name": "Renpei Yu"
                },
                {
                    "authorId": "143817222",
                    "name": "B. Iung"
                },
                {
                    "authorId": "1728242",
                    "name": "H. Panetto"
                }
            ],
            "doi": "10.1016/S0952-1976(03)00079-4",
            "intent": [
                "background"
            ],
            "isInfluential": false,
            "paperId": "85b7fea9ce11cc6abb1d53305329f26c73924940",
            "title": "A multi-agents based E-maintenance system with case-based reasoning decision support",
            "url": "https://www.semanticscholar.org/paper/85b7fea9ce11cc6abb1d53305329f26c73924940",
            "venue": "",
            "year": 2003
        },
        {
            "arxivId": null,
            "authors": [
                {
                    "authorId": "1732268",
                    "name": "A. Aamodt"
                },
                {
                    "authorId": "145863467",
                    "name": "E. Plaza"
                }
            ],
            "doi": "10.3233/AIC-1994-7104",
            "intent": [
                "methodology"
            ],
            "isInfluential": false,
            "paperId": "11f48f7ddd9cf79bc4351e8642efff2224757c9e",
            "title": "Case-Based Reasoning: Foundational Issues, Methodological Variations, and System Approaches",
            "url": "https://www.semanticscholar.org/paper/11f48f7ddd9cf79bc4351e8642efff2224757c9e",
            "venue": "AI Commun.",
            "year": 1994
        },
        {
            "arxivId": null,
            "authors": [
                {
                    "authorId": "2403310",
                    "name": "R. Schank"
                },
                {
                    "authorId": "1948269",
                    "name": "R. Abelson"
                }
            ],
            "doi": "10.2307/412850",
            "intent": [
                "background"
            ],
            "isInfluential": false,
            "paperId": "e2f6994f57e1a8b07de7d82bf0b751a52e1a887f",
            "title": "Scripts, plans, goals and understanding: an inquiry into human knowledge structures",
            "url": "https://www.semanticscholar.org/paper/e2f6994f57e1a8b07de7d82bf0b751a52e1a887f",
            "venue": "",
            "year": 1978
        },
        {
            "arxivId": "1810.04805",
            "authors": [
                {
                    "authorId": "39172707",
                    "name": "Jacob Devlin"
                },
                {
                    "authorId": "1744179",
                    "name": "Ming-Wei Chang"
                },
                {
                    "authorId": "2544107",
                    "name": "Kenton Lee"
                },
                {
                    "authorId": "3259253",
                    "name": "Kristina Toutanova"
                }
            ],
            "doi": "10.18653/v1/N19-1423",
            "intent": [
                "background"
            ],
            "isInfluential": false,
            "paperId": "df2b0e26d0599ce3e70df8a9da02e51594e0e992",
            "title": "BERT: Pre-training of Deep Bidirectional Transformers for Language Understanding",
            "url": "https://www.semanticscholar.org/paper/df2b0e26d0599ce3e70df8a9da02e51594e0e992",
            "venue": "NAACL",
            "year": 2019
        },
        {
            "arxivId": null,
            "authors": [
                {
                    "authorId": "1719404",
                    "name": "Alessandro Moschitti"
                },
                {
                    "authorId": "144865353",
                    "name": "B. Pang"
                },
                {
                    "authorId": "1735272",
                    "name": "Walter Daelemans"
                }
            ],
            "doi": "10.3115/v1/d14-1",
            "intent": [],
            "isInfluential": false,
            "paperId": "fdbb252f29ee0b72fc5467c0ae11f7cb30149f46",
            "title": "Proceedings of the 2014 Conference on Empirical Methods in Natural Language Processing (EMNLP)",
            "url": "https://www.semanticscholar.org/paper/fdbb252f29ee0b72fc5467c0ae11f7cb30149f46",
            "venue": "EMNLP 2014",
            "year": 2014
        },
        {
            "arxivId": null,
            "authors": [
                {
                    "authorId": "1730904",
                    "name": "C. Lucchese"
                },
                {
                    "authorId": "144263850",
                    "name": "Cristina Ioana Muntean"
                },
                {
                    "authorId": "2259557819",
                    "name": "Raffaele Perego"
                },
                {
                    "authorId": "2242324171",
                    "name": "Fabrizio Silvestri"
                },
                {
                    "authorId": "2273900730",
                    "name": "Hossein Vahabi"
                },
                {
                    "authorId": "1797933",
                    "name": "Rossano Venturini"
                }
            ],
            "doi": "10.1007/978-1-4614-6170-8_100614",
            "intent": [
                "background"
            ],
            "isInfluential": false,
            "paperId": "1f9be8eaf09e9c5a0c1b7178f1f96d77e636c39c",
            "title": "Recommender Systems",
            "url": "https://www.semanticscholar.org/paper/1f9be8eaf09e9c5a0c1b7178f1f96d77e636c39c",
            "venue": "Wirtschaftsinf.",
            "year": 2021
        },
        {
            "arxivId": null,
            "authors": [],
            "doi": null,
            "intent": [
                "background"
            ],
            "isInfluential": false,
            "paperId": "57238568414fd5786595f90103831f80b1d7037c",
            "title": "Dynamic memory - a theory of reminding and learning in computers and people",
            "url": "https://www.semanticscholar.org/paper/57238568414fd5786595f90103831f80b1d7037c",
            "venue": "",
            "year": 1983
        }
    ],
    "s2FieldsOfStudy": [
        {
            "category": "Computer Science",
            "source": "external"
        },
        {
            "category": "Computer Science",
            "source": "s2-fos-model"
        },
        {
            "category": "Business",
            "source": "s2-fos-model"
        }
    ],
    "title": "BRAIN L: A book recommender system",
    "topics": [],
    "url": "https://www.semanticscholar.org/paper/e5fd81c21f08690469dc9120bcc1e4c2bf28536f",
    "venue": "arXiv.org",
    "year": 2023
}