{
    "abstract": "This paper describes how to proficiently prevent software defects in autonomous vehicles, discover and correct defects if they are encountered, and create a higher level of assurance in the software product development phase. It also describes how to ensure high assurance on software reliability.",
    "arxivId": "2411.13614",
    "authors": [
        {
            "authorId": "2287840864",
            "name": "Sneha Sudhir Shetiya",
            "url": "https://www.semanticscholar.org/author/2287840864"
        },
        {
            "authorId": "2331613375",
            "name": "Vikas Vyas",
            "url": "https://www.semanticscholar.org/author/2331613375"
        },
        {
            "authorId": "2331613217",
            "name": "Shreyas Renukuntla",
            "url": "https://www.semanticscholar.org/author/2331613217"
        }
    ],
    "citationVelocity": 0,
    "citations": [],
    "corpusId": 274165553,
    "doi": null,
    "fieldsOfStudy": [
        "Computer Science"
    ],
    "influentialCitationCount": 0,
    "isOpenAccess": false,
    "isPublisherLicensed": true,
    "is_open_access": false,
    "is_publisher_licensed": true,
    "numCitedBy": 0,
    "numCiting": 0,
    "paperId": "8678d981213665ddb462c42bc1ec69749246753b",
    "references": [],
    "s2FieldsOfStudy": [
        {
            "category": "Computer Science",
            "source": "external"
        },
        {
            "category": "Engineering",
            "source": "s2-fos-model"
        },
        {
            "category": "Computer Science",
            "source": "s2-fos-model"
        }
    ],
    "title": "Verification and Validation of Autonomous Systems",
    "topics": [],
    "url": "https://www.semanticscholar.org/paper/8678d981213665ddb462c42bc1ec69749246753b",
    "venue": "",
    "year": 2024
}